{
  "version": 4,
  "description": "Curated city + island/landmark reference list for the Earth city-label layer (UX-11 #5). Offline-first; lat/lon in degrees. 'tier' drives zoom-based LOD: tier 1 = always shown (major cities + isolated ocean/remote references), tier 2 = medium zoom, tier 3 = close zoom only (dense-cluster / minor). Isolated references stay tier 1 so empty oceans always have a landmark.",
  "cities": [
    { "name": "New York",        "lat": 40.71,  "lon": -74.01,  "tier": 1 },
    { "name": "Washington",      "lat": 38.91,  "lon": -77.04,  "tier": 3 },
    { "name": "Toronto",         "lat": 43.65,  "lon": -79.38,  "tier": 2 },
    { "name": "Montreal",        "lat": 45.50,  "lon": -73.57,  "tier": 3 },
    { "name": "Chicago",         "lat": 41.88,  "lon": -87.63,  "tier": 2 },
    { "name": "Minneapolis",     "lat": 44.98,  "lon": -93.27,  "tier": 3 },
    { "name": "Atlanta",         "lat": 33.75,  "lon": -84.39,  "tier": 3 },
    { "name": "Miami",           "lat": 25.76,  "lon": -80.19,  "tier": 2 },
    { "name": "Houston",         "lat": 29.76,  "lon": -95.37,  "tier": 2 },
    { "name": "Dallas",          "lat": 32.78,  "lon": -96.80,  "tier": 3 },
    { "name": "Denver",          "lat": 39.74,  "lon": -104.99, "tier": 2 },
    { "name": "Phoenix",         "lat": 33.45,  "lon": -112.07, "tier": 3 },
    { "name": "Los Angeles",     "lat": 34.05,  "lon": -118.24, "tier": 1 },
    { "name": "San Francisco",   "lat": 37.77,  "lon": -122.42, "tier": 2 },
    { "name": "Seattle",         "lat": 47.61,  "lon": -122.33, "tier": 2 },
    { "name": "Vancouver",       "lat": 49.28,  "lon": -123.12, "tier": 3 },
    { "name": "Calgary",         "lat": 51.05,  "lon": -114.07, "tier": 3 },
    { "name": "Winnipeg",        "lat": 49.90,  "lon": -97.14,  "tier": 3 },
    { "name": "Anchorage",       "lat": 61.22,  "lon": -149.90, "tier": 2 },
    { "name": "Yellowknife",     "lat": 62.45,  "lon": -114.37, "tier": 2 },
    { "name": "Nuuk",            "lat": 64.18,  "lon": -51.69,  "tier": 1 },
    { "name": "Honolulu",        "lat": 21.31,  "lon": -157.86, "tier": 1 },
    { "name": "Midway",          "lat": 28.21,  "lon": -177.38, "tier": 2 },
    { "name": "Guadalajara",     "lat": 20.67,  "lon": -103.35, "tier": 3 },
    { "name": "Monterrey",       "lat": 25.69,  "lon": -100.32, "tier": 3 },
    { "name": "Mexico City",     "lat": 19.43,  "lon": -99.13,  "tier": 1 },
    { "name": "Havana",          "lat": 23.11,  "lon": -82.37,  "tier": 2 },
    { "name": "Nassau",          "lat": 25.06,  "lon": -77.34,  "tier": 3 },
    { "name": "Bermuda",         "lat": 32.29,  "lon": -64.78,  "tier": 2 },
    { "name": "Santo Domingo",   "lat": 18.49,  "lon": -69.93,  "tier": 3 },
    { "name": "San Juan",        "lat": 18.47,  "lon": -66.10,  "tier": 3 },
    { "name": "Kingston",        "lat": 17.97,  "lon": -76.79,  "tier": 3 },
    { "name": "Guatemala City",  "lat": 14.63,  "lon": -90.51,  "tier": 3 },
    { "name": "San Jose",        "lat": 9.93,   "lon": -84.08,  "tier": 3 },
    { "name": "Panama City",     "lat": 8.98,   "lon": -79.52,  "tier": 2 },
    { "name": "Bogota",          "lat": 4.71,   "lon": -74.07,  "tier": 2 },
    { "name": "Caracas",         "lat": 10.48,  "lon": -66.90,  "tier": 2 },
    { "name": "Quito",           "lat": -0.18,  "lon": -78.47,  "tier": 3 },
    { "name": "Galapagos",       "lat": -0.74,  "lon": -90.31,  "tier": 1 },
    { "name": "Lima",            "lat": -12.05, "lon": -77.04,  "tier": 2 },
    { "name": "La Paz",          "lat": -16.50, "lon": -68.15,  "tier": 3 },
    { "name": "Santiago",        "lat": -33.45, "lon": -70.67,  "tier": 2 },
    { "name": "Buenos Aires",    "lat": -34.60, "lon": -58.38,  "tier": 1 },
    { "name": "Montevideo",      "lat": -34.90, "lon": -56.16,  "tier": 3 },
    { "name": "Asuncion",        "lat": -25.30, "lon": -57.64,  "tier": 3 },
    { "name": "Brasilia",        "lat": -15.79, "lon": -47.88,  "tier": 2 },
    { "name": "Manaus",          "lat": -3.12,  "lon": -60.02,  "tier": 2 },
    { "name": "Recife",          "lat": -8.05,  "lon": -34.88,  "tier": 3 },
    { "name": "Sao Paulo",       "lat": -23.55, "lon": -46.63,  "tier": 1 },
    { "name": "Rio de Janeiro",  "lat": -22.91, "lon": -43.17,  "tier": 1 },
    { "name": "Falklands",       "lat": -51.69, "lon": -57.85,  "tier": 1 },
    { "name": "Reykjavik",       "lat": 64.15,  "lon": -21.94,  "tier": 1 },
    { "name": "Azores",          "lat": 37.74,  "lon": -25.67,  "tier": 1 },
    { "name": "Dublin",          "lat": 53.35,  "lon": -6.26,   "tier": 3 },
    { "name": "London",          "lat": 51.51,  "lon": -0.13,   "tier": 1 },
    { "name": "Lisbon",          "lat": 38.72,  "lon": -9.14,   "tier": 2 },
    { "name": "Madrid",          "lat": 40.42,  "lon": -3.70,   "tier": 1 },
    { "name": "Barcelona",       "lat": 41.39,  "lon": 2.17,    "tier": 3 },
    { "name": "Paris",           "lat": 48.86,  "lon": 2.35,    "tier": 1 },
    { "name": "Amsterdam",       "lat": 52.37,  "lon": 4.90,    "tier": 3 },
    { "name": "Brussels",        "lat": 50.85,  "lon": 4.35,    "tier": 3 },
    { "name": "Berlin",          "lat": 52.52,  "lon": 13.41,   "tier": 1 },
    { "name": "Rome",            "lat": 41.90,  "lon": 12.50,   "tier": 1 },
    { "name": "Vienna",          "lat": 48.21,  "lon": 16.37,   "tier": 3 },
    { "name": "Zurich",          "lat": 47.37,  "lon": 8.54,    "tier": 3 },
    { "name": "Stockholm",       "lat": 59.33,  "lon": 18.07,   "tier": 2 },
    { "name": "Oslo",            "lat": 59.91,  "lon": 10.75,   "tier": 3 },
    { "name": "Tromso",          "lat": 69.65,  "lon": 18.96,   "tier": 2 },
    { "name": "Copenhagen",      "lat": 55.68,  "lon": 12.57,   "tier": 3 },
    { "name": "Helsinki",        "lat": 60.17,  "lon": 24.94,   "tier": 3 },
    { "name": "Warsaw",          "lat": 52.23,  "lon": 21.01,   "tier": 2 },
    { "name": "Athens",          "lat": 37.98,  "lon": 23.73,   "tier": 2 },
    { "name": "Kyiv",            "lat": 50.45,  "lon": 30.52,   "tier": 2 },
    { "name": "Moscow",          "lat": 55.76,  "lon": 37.62,   "tier": 1 },
    { "name": "Istanbul",        "lat": 41.01,  "lon": 28.98,   "tier": 1 },
    { "name": "Canary Is",       "lat": 28.12,  "lon": -15.44,  "tier": 1 },
    { "name": "Casablanca",      "lat": 33.57,  "lon": -7.59,   "tier": 2 },
    { "name": "Marrakech",       "lat": 31.63,  "lon": -7.99,   "tier": 3 },
    { "name": "Algiers",         "lat": 36.75,  "lon": 3.06,    "tier": 2 },
    { "name": "Tunis",           "lat": 36.81,  "lon": 10.18,   "tier": 3 },
    { "name": "Tripoli",         "lat": 32.89,  "lon": 13.19,   "tier": 2 },
    { "name": "Cairo",           "lat": 30.04,  "lon": 31.24,   "tier": 1 },
    { "name": "Cape Verde",      "lat": 14.93,  "lon": -23.51,  "tier": 1 },
    { "name": "Dakar",           "lat": 14.69,  "lon": -17.45,  "tier": 2 },
    { "name": "Bamako",          "lat": 12.65,  "lon": -8.00,   "tier": 2 },
    { "name": "Kano",            "lat": 12.00,  "lon": 8.52,    "tier": 3 },
    { "name": "Lagos",           "lat": 6.52,   "lon": 3.38,    "tier": 1 },
    { "name": "Accra",           "lat": 5.60,   "lon": -0.19,   "tier": 2 },
    { "name": "Abidjan",         "lat": 5.36,   "lon": -4.01,   "tier": 3 },
    { "name": "Khartoum",        "lat": 15.50,  "lon": 32.56,   "tier": 2 },
    { "name": "Addis Ababa",     "lat": 9.03,   "lon": 38.74,   "tier": 2 },
    { "name": "Mogadishu",       "lat": 2.05,   "lon": 45.34,   "tier": 2 },
    { "name": "Nairobi",         "lat": -1.29,  "lon": 36.82,   "tier": 1 },
    { "name": "Kampala",         "lat": 0.35,   "lon": 32.58,   "tier": 3 },
    { "name": "Dar es Salaam",   "lat": -6.79,  "lon": 39.21,   "tier": 3 },
    { "name": "Kinshasa",        "lat": -4.32,  "lon": 15.31,   "tier": 2 },
    { "name": "Luanda",          "lat": -8.84,  "lon": 13.23,   "tier": 2 },
    { "name": "Lusaka",          "lat": -15.42, "lon": 28.28,   "tier": 3 },
    { "name": "Harare",          "lat": -17.83, "lon": 31.05,   "tier": 3 },
    { "name": "Maputo",          "lat": -25.97, "lon": 32.57,   "tier": 3 },
    { "name": "Windhoek",        "lat": -22.56, "lon": 17.08,   "tier": 2 },
    { "name": "Johannesburg",    "lat": -26.20, "lon": 28.05,   "tier": 1 },
    { "name": "Cape Town",       "lat": -33.92, "lon": 18.42,   "tier": 2 },
    { "name": "Antananarivo",    "lat": -18.88, "lon": 47.51,   "tier": 2 },
    { "name": "Mauritius",       "lat": -20.16, "lon": 57.50,   "tier": 1 },
    { "name": "Seychelles",      "lat": -4.62,  "lon": 55.45,   "tier": 1 },
    { "name": "Tel Aviv",        "lat": 32.08,  "lon": 34.78,   "tier": 2 },
    { "name": "Beirut",          "lat": 33.89,  "lon": 35.50,   "tier": 3 },
    { "name": "Amman",           "lat": 31.95,  "lon": 35.93,   "tier": 3 },
    { "name": "Baghdad",         "lat": 33.31,  "lon": 44.36,   "tier": 2 },
    { "name": "Riyadh",          "lat": 24.71,  "lon": 46.68,   "tier": 1 },
    { "name": "Jeddah",          "lat": 21.49,  "lon": 39.19,   "tier": 3 },
    { "name": "Kuwait City",     "lat": 29.38,  "lon": 47.99,   "tier": 3 },
    { "name": "Doha",            "lat": 25.29,  "lon": 51.53,   "tier": 3 },
    { "name": "Dubai",           "lat": 25.20,  "lon": 55.27,   "tier": 1 },
    { "name": "Muscat",          "lat": 23.59,  "lon": 58.41,   "tier": 3 },
    { "name": "Sanaa",           "lat": 15.37,  "lon": 44.19,   "tier": 3 },
    { "name": "Tehran",          "lat": 35.69,  "lon": 51.39,   "tier": 1 },
    { "name": "Kabul",           "lat": 34.53,  "lon": 69.17,   "tier": 2 },
    { "name": "Karachi",         "lat": 24.86,  "lon": 67.01,   "tier": 2 },
    { "name": "Mumbai",          "lat": 19.08,  "lon": 72.88,   "tier": 1 },
    { "name": "Delhi",           "lat": 28.61,  "lon": 77.21,   "tier": 1 },
    { "name": "Bangalore",       "lat": 12.97,  "lon": 77.59,   "tier": 2 },
    { "name": "Colombo",         "lat": 6.93,   "lon": 79.85,   "tier": 2 },
    { "name": "Maldives",        "lat": 4.18,   "lon": 73.51,   "tier": 1 },
    { "name": "Kathmandu",       "lat": 27.72,  "lon": 85.32,   "tier": 3 },
    { "name": "Dhaka",           "lat": 23.81,  "lon": 90.41,   "tier": 2 },
    { "name": "Tashkent",        "lat": 41.30,  "lon": 69.24,   "tier": 2 },
    { "name": "Almaty",          "lat": 43.24,  "lon": 76.89,   "tier": 3 },
    { "name": "Astana",          "lat": 51.17,  "lon": 71.43,   "tier": 2 },
    { "name": "Bishkek",         "lat": 42.87,  "lon": 74.59,   "tier": 3 },
    { "name": "Novosibirsk",     "lat": 55.01,  "lon": 82.93,   "tier": 2 },
    { "name": "Ulaanbaatar",     "lat": 47.89,  "lon": 106.91,  "tier": 2 },
    { "name": "Irkutsk",         "lat": 52.29,  "lon": 104.30,  "tier": 3 },
    { "name": "Yakutsk",         "lat": 62.04,  "lon": 129.73,  "tier": 2 },
    { "name": "Vladivostok",     "lat": 43.12,  "lon": 131.89,  "tier": 2 },
    { "name": "Beijing",         "lat": 39.90,  "lon": 116.41,  "tier": 1 },
    { "name": "Chengdu",         "lat": 30.57,  "lon": 104.07,  "tier": 3 },
    { "name": "Shanghai",        "lat": 31.23,  "lon": 121.47,  "tier": 1 },
    { "name": "Guangzhou",       "lat": 23.13,  "lon": 113.26,  "tier": 3 },
    { "name": "Hong Kong",       "lat": 22.32,  "lon": 114.17,  "tier": 1 },
    { "name": "Taipei",          "lat": 25.03,  "lon": 121.57,  "tier": 2 },
    { "name": "Seoul",           "lat": 37.57,  "lon": 126.98,  "tier": 1 },
    { "name": "Tokyo",           "lat": 35.68,  "lon": 139.69,  "tier": 1 },
    { "name": "Osaka",           "lat": 34.69,  "lon": 135.50,  "tier": 3 },
    { "name": "Sapporo",         "lat": 43.06,  "lon": 141.35,  "tier": 3 },
    { "name": "Bangkok",         "lat": 13.76,  "lon": 100.50,  "tier": 1 },
    { "name": "Ho Chi Minh",     "lat": 10.82,  "lon": 106.63,  "tier": 2 },
    { "name": "Kuala Lumpur",    "lat": 3.14,   "lon": 101.69,  "tier": 2 },
    { "name": "Singapore",       "lat": 1.35,   "lon": 103.82,  "tier": 1 },
    { "name": "Jakarta",         "lat": -6.21,  "lon": 106.85,  "tier": 1 },
    { "name": "Manila",          "lat": 14.60,  "lon": 120.98,  "tier": 1 },
    { "name": "Guam",            "lat": 13.44,  "lon": 144.79,  "tier": 1 },
    { "name": "Perth",           "lat": -31.95, "lon": 115.86,  "tier": 2 },
    { "name": "Darwin",          "lat": -12.46, "lon": 130.84,  "tier": 2 },
    { "name": "Alice Springs",   "lat": -23.70, "lon": 133.88,  "tier": 2 },
    { "name": "Adelaide",        "lat": -34.93, "lon": 138.60,  "tier": 3 },
    { "name": "Brisbane",        "lat": -27.47, "lon": 153.03,  "tier": 3 },
    { "name": "Sydney",          "lat": -33.87, "lon": 151.21,  "tier": 1 },
    { "name": "Melbourne",       "lat": -37.81, "lon": 144.96,  "tier": 2 },
    { "name": "Auckland",        "lat": -36.85, "lon": 174.76,  "tier": 1 },
    { "name": "Wellington",      "lat": -41.29, "lon": 174.78,  "tier": 3 },
    { "name": "Port Moresby",    "lat": -9.44,  "lon": 147.18,  "tier": 2 },
    { "name": "Honiara",         "lat": -9.43,  "lon": 159.95,  "tier": 1 },
    { "name": "Noumea",          "lat": -22.28, "lon": 166.46,  "tier": 2 },
    { "name": "Suva",            "lat": -18.14, "lon": 178.44,  "tier": 1 },
    { "name": "Apia",            "lat": -13.83, "lon": -171.77, "tier": 1 },
    { "name": "Tahiti",          "lat": -17.54, "lon": -149.57, "tier": 1 },
    { "name": "Easter Is",       "lat": -27.11, "lon": -109.35, "tier": 1 },
    { "name": "Pitcairn",        "lat": -25.07, "lon": -130.10, "tier": 1 },
    { "name": "Marquesas",       "lat": -8.92,  "lon": -140.10, "tier": 1 },
    { "name": "Kiritimati",      "lat": 1.87,   "lon": -157.43, "tier": 1 },
    { "name": "Wake Is",         "lat": 19.28,  "lon": 166.65,  "tier": 1 },
    { "name": "Marshall Is",     "lat": 7.12,   "lon": 171.18,  "tier": 1 },
    { "name": "Diego Garcia",    "lat": -7.31,  "lon": 72.41,   "tier": 1 },
    { "name": "Cocos Is",        "lat": -12.17, "lon": 96.83,   "tier": 1 },
    { "name": "Christmas Is",    "lat": -10.49, "lon": 105.62,  "tier": 1 },
    { "name": "Ascension",       "lat": -7.95,  "lon": -14.36,  "tier": 1 },
    { "name": "St Helena",       "lat": -15.96, "lon": -5.71,   "tier": 1 },
    { "name": "Tristan",         "lat": -37.11, "lon": -12.28,  "tier": 1 },
    { "name": "McMurdo",         "lat": -77.85, "lon": 166.67,  "tier": 1 }
  ]
}
